{"time":{"updated":"Jun 26, 2024 22:50:01 UTC","updatedISO":"2024-06-26T22:50:01+00:00","updateduk":"Jun 26, 2024 at 23:50 BST"},"disclaimer":"This data was produced from the CoinDesk Bitcoin Price Index (USD). Non-USD currency data converted using hourly conversion rate from openexchangerates.org","chartName":"Bitcoin","bpi":{"USD":{"code":"USD","symbol":"&#36;","rate":"60,843.894","description":"United States Dollar","rate_float":60843.8944},"GBP":{"code":"GBP","symbol":"&pound;","rate":"48,202.237","description":"British Pound Sterling","rate_float":48202.2368},"EUR":{"code":"EUR","symbol":"&euro;","rate":"56,968.138","description":"Euro","rate_float":56968.1384},"CNY":{"code":"CNY","symbol":"&yen;","rate":"442,018.724","description":"Chinese Yuan","rate_float":442018.7243}}}