{"time":{"updated":"Jan 2, 2022 15:12:00 UTC","updatedISO":"2022-01-02T15:12:00+00:00","updateduk":"Jan 2, 2022 at 15:12 GMT"},"disclaimer":"This data was produced from the CoinDesk Bitcoin Price Index (USD). Non-USD currency data converted using hourly conversion rate from openexchangerates.org","chartName":"Bitcoin","bpi":{"USD":{"code":"USD","symbol":"&#36;","rate":"47,193.3433","description":"United States Dollar","rate_float":47193.3433},"GBP":{"code":"GBP","symbol":"&pound;","rate":"34,876.6358","description":"British Pound Sterling","rate_float":34876.6358},"EUR":{"code":"EUR","symbol":"&euro;","rate":"41,492.4818","description":"Euro","rate_float":41492.4818},"CNY":{"code":"CNY","symbol":"&yen;","rate":"40,202.5000","description":"Chinese Yuan","rate_float":40202.5}}}