{"time":{"updated":"Feb 23, 2024 04:07:01 UTC","updatedISO":"2024-02-23T04:07:01+00:00","updateduk":"Feb 23, 2024 at 04:07 GMT"},"disclaimer":"This data was produced from the CoinDesk Bitcoin Price Index (USD). Non-USD currency data converted using hourly conversion rate from openexchangerates.org","chartName":"Bitcoin","bpi":{"USD":{"code":"USD","symbol":"&#36;","rate":"51,101.098","description":"United States Dollar","rate_float":51101.0975},"GBP":{"code":"GBP","symbol":"&pound;","rate":"40,350.806","description":"British Pound Sterling","rate_float":40350.8063},"EUR":{"code":"EUR","symbol":"&euro;","rate":"47,204.843","description":"Euro","rate_float":47204.8432},"CNY":{"code":"CNY","symbol":"&yen;","rate":"367,718.388","description":"Chinese Yuan","rate_float":367718.3876}}}