{"time":{"updated":"Jan 18, 2024 15:24:06 UTC","updatedISO":"2024-01-18T15:24:06+00:00","updateduk":"Jan 18, 2024 at 15:24 GMT"},"disclaimer":"This data was produced from the CoinDesk Bitcoin Price Index (USD). Non-USD currency data converted using hourly conversion rate from openexchangerates.org","chartName":"Bitcoin","bpi":{"USD":{"code":"USD","symbol":"&#36;","rate":"42,734.124","description":"United States Dollar","rate_float":42734.1236},"GBP":{"code":"GBP","symbol":"&pound;","rate":"33,774.744","description":"British Pound Sterling","rate_float":33774.7436},"EUR":{"code":"EUR","symbol":"&euro;","rate":"39,377.23","description":"Euro","rate_float":39377.23},"CNY":{"code":"CNY","symbol":"&yen;","rate":"304,352.428","description":"Chinese Yuan","rate_float":304352.4282}}}