{"time":{"updated":"Apr 15, 2024 04:12:52 UTC","updatedISO":"2024-04-15T04:12:52+00:00","updateduk":"Apr 15, 2024 at 05:12 BST"},"disclaimer":"This data was produced from the CoinDesk Bitcoin Price Index (USD). Non-USD currency data converted using hourly conversion rate from openexchangerates.org","chartName":"Bitcoin","bpi":{"USD":{"code":"USD","symbol":"&#36;","rate":"65,114.676","description":"United States Dollar","rate_float":65114.6757},"GBP":{"code":"GBP","symbol":"&pound;","rate":"52,258.369","description":"British Pound Sterling","rate_float":52258.369},"EUR":{"code":"EUR","symbol":"&euro;","rate":"61,136.495","description":"Euro","rate_float":61136.4946},"CNY":{"code":"CNY","symbol":"&yen;","rate":"471,313.046","description":"Chinese Yuan","rate_float":471313.0458}}}