{"time":{"updated":"Mar 15, 2024 19:43:00 UTC","updatedISO":"2024-03-15T19:43:00+00:00","updateduk":"Mar 15, 2024 at 19:43 GMT"},"disclaimer":"This data was produced from the CoinDesk Bitcoin Price Index (USD). Non-USD currency data converted using hourly conversion rate from openexchangerates.org","chartName":"Bitcoin","bpi":{"USD":{"code":"USD","symbol":"&#36;","rate":"69,562.899","description":"United States Dollar","rate_float":69562.8987},"GBP":{"code":"GBP","symbol":"&pound;","rate":"54,605.623","description":"British Pound Sterling","rate_float":54605.6233},"EUR":{"code":"EUR","symbol":"&euro;","rate":"63,873.975","description":"Euro","rate_float":63873.9752},"CNY":{"code":"CNY","symbol":"&yen;","rate":"500,574.619","description":"Chinese Yuan","rate_float":500574.6188}}}