{"time":{"updated":"Oct 14, 2024 20:56:41 UTC","updatedISO":"2024-10-14T20:56:41+00:00","updateduk":"Oct 14, 2024 at 21:56 BST"},"disclaimer":"This data was produced from the CoinDesk Bitcoin Price Index (USD). Non-USD currency data converted using hourly conversion rate from openexchangerates.org","chartName":"Bitcoin","bpi":{"USD":{"code":"USD","symbol":"&#36;","rate":"65,864.736","description":"United States Dollar","rate_float":65864.7355},"GBP":{"code":"GBP","symbol":"&pound;","rate":"50,450.28","description":"British Pound Sterling","rate_float":50450.2797},"EUR":{"code":"EUR","symbol":"&euro;","rate":"60,404.549","description":"Euro","rate_float":60404.5489},"CNY":{"code":"CNY","symbol":"&yen;","rate":"466,875.591","description":"Chinese Yuan","rate_float":466875.591}}}