{"time":{"updated":"Jan 28, 2025 19:59:59 UTC","updatedISO":"2025-01-28T19:59:59+00:00","updateduk":"Jan 28, 2025 at 19:59 GMT"},"disclaimer":"This data was produced from the CoinDesk Bitcoin Price Index (USD). Non-USD currency data converted using hourly conversion rate from openexchangerates.org","chartName":"Bitcoin","bpi":{"USD":{"code":"USD","symbol":"&#36;","rate":"102,665.921","description":"United States Dollar","rate_float":102665.9206},"GBP":{"code":"GBP","symbol":"&pound;","rate":"82,449.666","description":"British Pound Sterling","rate_float":82449.6662},"EUR":{"code":"EUR","symbol":"&euro;","rate":"98,156.525","description":"Euro","rate_float":98156.5254},"CNY":{"code":"CNY","symbol":"&yen;","rate":"746,042.445","description":"Chinese Yuan","rate_float":746042.4454}}}