{"time":{"updated":"Nov 19, 2024 21:25:09 UTC","updatedISO":"2024-11-19T21:25:09+00:00","updateduk":"Nov 19, 2024 at 21:25 GMT"},"disclaimer":"This data was produced from the CoinDesk Bitcoin Price Index (USD). Non-USD currency data converted using hourly conversion rate from openexchangerates.org","chartName":"Bitcoin","bpi":{"USD":{"code":"USD","symbol":"&#36;","rate":"92,022.189","description":"United States Dollar","rate_float":92022.1885},"GBP":{"code":"GBP","symbol":"&pound;","rate":"72,585.262","description":"British Pound Sterling","rate_float":72585.2619},"EUR":{"code":"EUR","symbol":"&euro;","rate":"86,863.333","description":"Euro","rate_float":86863.3326},"CNY":{"code":"CNY","symbol":"&yen;","rate":"666,176.23","description":"Chinese Yuan","rate_float":666176.2295}}}