{"time":{"updated":"Dec 1, 2022 14:59:00 UTC","updatedISO":"2022-12-01T14:59:00+00:00","updateduk":"Dec 1, 2022 at 14:59 GMT"},"disclaimer":"This data was produced from the CoinDesk Bitcoin Price Index (USD). Non-USD currency data converted using hourly conversion rate from openexchangerates.org","chartName":"Bitcoin","bpi":{"USD":{"code":"USD","symbol":"&#36;","rate":"17,101.2200","description":"United States Dollar","rate_float":17101.22},"GBP":{"code":"GBP","symbol":"&pound;","rate":"14,289.6426","description":"British Pound Sterling","rate_float":14289.6426},"EUR":{"code":"EUR","symbol":"&euro;","rate":"16,659.0851","description":"Euro","rate_float":16659.0851},"CNY":{"code":"CNY","symbol":"&yen;","rate":"40,202.5000","description":"Chinese Yuan","rate_float":40202.5}}}