{"time":{"updated":"Feb 20, 2024 22:40:13 UTC","updatedISO":"2024-02-20T22:40:13+00:00","updateduk":"Feb 20, 2024 at 22:40 GMT"},"disclaimer":"This data was produced from the CoinDesk Bitcoin Price Index (USD). Non-USD currency data converted using hourly conversion rate from openexchangerates.org","chartName":"Bitcoin","bpi":{"USD":{"code":"USD","symbol":"&#36;","rate":"52,276.122","description":"United States Dollar","rate_float":52276.1218},"GBP":{"code":"GBP","symbol":"&pound;","rate":"41,414.817","description":"British Pound Sterling","rate_float":41414.8165},"EUR":{"code":"EUR","symbol":"&euro;","rate":"48,369.161","description":"Euro","rate_float":48369.1612},"CNY":{"code":"CNY","symbol":"&yen;","rate":"375,954.185","description":"Chinese Yuan","rate_float":375954.1848}}}