{"time":{"updated":"Dec 24, 2021 07:51:00 UTC","updatedISO":"2021-12-24T07:51:00+00:00","updateduk":"Dec 24, 2021 at 07:51 GMT"},"disclaimer":"This data was produced from the CoinDesk Bitcoin Price Index (USD). Non-USD currency data converted using hourly conversion rate from openexchangerates.org","chartName":"Bitcoin","bpi":{"USD":{"code":"USD","symbol":"&#36;","rate":"50,997.1407","description":"United States Dollar","rate_float":50997.1407},"GBP":{"code":"GBP","symbol":"&pound;","rate":"38,046.7228","description":"British Pound Sterling","rate_float":38046.7228},"EUR":{"code":"EUR","symbol":"&euro;","rate":"45,012.3202","description":"Euro","rate_float":45012.3202},"CNY":{"code":"CNY","symbol":"&yen;","rate":"40,202.5000","description":"Chinese Yuan","rate_float":40202.5}}}