{"time":{"updated":"Jul 16, 2024 03:53:21 UTC","updatedISO":"2024-07-16T03:53:21+00:00","updateduk":"Jul 16, 2024 at 04:53 BST"},"disclaimer":"This data was produced from the CoinDesk Bitcoin Price Index (USD). Non-USD currency data converted using hourly conversion rate from openexchangerates.org","chartName":"Bitcoin","bpi":{"USD":{"code":"USD","symbol":"&#36;","rate":"64,806.911","description":"United States Dollar","rate_float":64806.9111},"GBP":{"code":"GBP","symbol":"&pound;","rate":"49,992.635","description":"British Pound Sterling","rate_float":49992.6345},"EUR":{"code":"EUR","symbol":"&euro;","rate":"59,504.021","description":"Euro","rate_float":59504.0208},"CNY":{"code":"CNY","symbol":"&yen;","rate":"470,491.694","description":"Chinese Yuan","rate_float":470491.6936}}}