{"time":{"updated":"Jul 29, 2024 08:51:43 UTC","updatedISO":"2024-07-29T08:51:43+00:00","updateduk":"Jul 29, 2024 at 09:51 BST"},"disclaimer":"This data was produced from the CoinDesk Bitcoin Price Index (USD). Non-USD currency data converted using hourly conversion rate from openexchangerates.org","chartName":"Bitcoin","bpi":{"USD":{"code":"USD","symbol":"&#36;","rate":"69,503.656","description":"United States Dollar","rate_float":69503.6558},"GBP":{"code":"GBP","symbol":"&pound;","rate":"54,159.125","description":"British Pound Sterling","rate_float":54159.1252},"EUR":{"code":"EUR","symbol":"&euro;","rate":"64,088.139","description":"Euro","rate_float":64088.1394},"CNY":{"code":"CNY","symbol":"&yen;","rate":"504,388.03","description":"Chinese Yuan","rate_float":504388.03}}}