{"time":{"updated":"Dec 2, 2022 21:35:00 UTC","updatedISO":"2022-12-02T21:35:00+00:00","updateduk":"Dec 2, 2022 at 21:35 GMT"},"disclaimer":"This data was produced from the CoinDesk Bitcoin Price Index (USD). Non-USD currency data converted using hourly conversion rate from openexchangerates.org","chartName":"Bitcoin","bpi":{"USD":{"code":"USD","symbol":"&#36;","rate":"17,010.8059","description":"United States Dollar","rate_float":17010.8059},"GBP":{"code":"GBP","symbol":"&pound;","rate":"14,214.0933","description":"British Pound Sterling","rate_float":14214.0933},"EUR":{"code":"EUR","symbol":"&euro;","rate":"16,571.0085","description":"Euro","rate_float":16571.0085},"CNY":{"code":"CNY","symbol":"&yen;","rate":"40,202.5000","description":"Chinese Yuan","rate_float":40202.5}}}