{"time":{"updated":"Oct 23, 2024 09:47:04 UTC","updatedISO":"2024-10-23T09:47:04+00:00","updateduk":"Oct 23, 2024 at 10:47 BST"},"disclaimer":"This data was produced from the CoinDesk Bitcoin Price Index (USD). Non-USD currency data converted using hourly conversion rate from openexchangerates.org","chartName":"Bitcoin","bpi":{"USD":{"code":"USD","symbol":"&#36;","rate":"66,480.565","description":"United States Dollar","rate_float":66480.5648},"GBP":{"code":"GBP","symbol":"&pound;","rate":"51,202.068","description":"British Pound Sterling","rate_float":51202.0678},"EUR":{"code":"EUR","symbol":"&euro;","rate":"61,623.428","description":"Euro","rate_float":61623.4282},"CNY":{"code":"CNY","symbol":"&yen;","rate":"473,760.449","description":"Chinese Yuan","rate_float":473760.4486}}}