{"time":{"updated":"Dec 17, 2023 19:38:00 UTC","updatedISO":"2023-12-17T19:38:00+00:00","updateduk":"Dec 17, 2023 at 19:38 GMT"},"disclaimer":"This data was produced from the CoinDesk Bitcoin Price Index (USD). Non-USD currency data converted using hourly conversion rate from openexchangerates.org","chartName":"Bitcoin","bpi":{"USD":{"code":"USD","symbol":"&#36;","rate":"42,048.6077","description":"United States Dollar","rate_float":42048.6077},"GBP":{"code":"GBP","symbol":"&pound;","rate":"35,135.4802","description":"British Pound Sterling","rate_float":35135.4802},"EUR":{"code":"EUR","symbol":"&euro;","rate":"40,961.4830","description":"Euro","rate_float":40961.483},"CNY":{"code":"CNY","symbol":"&yen;","rate":"40,202.5000","description":"Chinese Yuan","rate_float":40202.5}}}