{"time":{"updated":"Jul 28, 2024 21:18:55 UTC","updatedISO":"2024-07-28T21:18:55+00:00","updateduk":"Jul 28, 2024 at 22:18 BST"},"disclaimer":"This data was produced from the CoinDesk Bitcoin Price Index (USD). Non-USD currency data converted using hourly conversion rate from openexchangerates.org","chartName":"Bitcoin","bpi":{"USD":{"code":"USD","symbol":"&#36;","rate":"67,942.122","description":"United States Dollar","rate_float":67942.1218},"GBP":{"code":"GBP","symbol":"&pound;","rate":"52,817.934","description":"British Pound Sterling","rate_float":52817.9337},"EUR":{"code":"EUR","symbol":"&euro;","rate":"62,560.155","description":"Euro","rate_float":62560.1546},"CNY":{"code":"CNY","symbol":"&yen;","rate":"492,607.56","description":"Chinese Yuan","rate_float":492607.56}}}