{"time":{"updated":"Jul 1, 2024 03:07:25 UTC","updatedISO":"2024-07-01T03:07:25+00:00","updateduk":"Jul 1, 2024 at 04:07 BST"},"disclaimer":"This data was produced from the CoinDesk Bitcoin Price Index (USD). Non-USD currency data converted using hourly conversion rate from openexchangerates.org","chartName":"Bitcoin","bpi":{"USD":{"code":"USD","symbol":"&#36;","rate":"63,432.651","description":"United States Dollar","rate_float":63432.6511},"GBP":{"code":"GBP","symbol":"&pound;","rate":"50,109.701","description":"British Pound Sterling","rate_float":50109.7011},"EUR":{"code":"EUR","symbol":"&euro;","rate":"59,016.66","description":"Euro","rate_float":59016.6603},"CNY":{"code":"CNY","symbol":"&yen;","rate":"460,996.792","description":"Chinese Yuan","rate_float":460996.7922}}}