{"time":{"updated":"Nov 18, 2022 03:58:00 UTC","updatedISO":"2022-11-18T03:58:00+00:00","updateduk":"Nov 18, 2022 at 03:58 GMT"},"disclaimer":"This data was produced from the CoinDesk Bitcoin Price Index (USD). Non-USD currency data converted using hourly conversion rate from openexchangerates.org","chartName":"Bitcoin","bpi":{"USD":{"code":"USD","symbol":"&#36;","rate":"16,830.7218","description":"United States Dollar","rate_float":16830.7218},"GBP":{"code":"GBP","symbol":"&pound;","rate":"14,063.6164","description":"British Pound Sterling","rate_float":14063.6164},"EUR":{"code":"EUR","symbol":"&euro;","rate":"16,395.5803","description":"Euro","rate_float":16395.5803},"CNY":{"code":"CNY","symbol":"&yen;","rate":"40,202.5000","description":"Chinese Yuan","rate_float":40202.5}}}