{"time":{"updated":"Mar 4, 2024 20:22:37 UTC","updatedISO":"2024-03-04T20:22:37+00:00","updateduk":"Mar 4, 2024 at 20:22 GMT"},"disclaimer":"This data was produced from the CoinDesk Bitcoin Price Index (USD). Non-USD currency data converted using hourly conversion rate from openexchangerates.org","chartName":"Bitcoin","bpi":{"USD":{"code":"USD","symbol":"&#36;","rate":"67,239.796","description":"United States Dollar","rate_float":67239.7963},"GBP":{"code":"GBP","symbol":"&pound;","rate":"52,983.279","description":"British Pound Sterling","rate_float":52983.2785},"EUR":{"code":"EUR","symbol":"&euro;","rate":"61,934.913","description":"Euro","rate_float":61934.9126},"CNY":{"code":"CNY","symbol":"&yen;","rate":"484,092.914","description":"Chinese Yuan","rate_float":484092.9137}}}