{"time":{"updated":"Dec 21, 2022 14:49:00 UTC","updatedISO":"2022-12-21T14:49:00+00:00","updateduk":"Dec 21, 2022 at 14:49 GMT"},"disclaimer":"This data was produced from the CoinDesk Bitcoin Price Index (USD). Non-USD currency data converted using hourly conversion rate from openexchangerates.org","chartName":"Bitcoin","bpi":{"USD":{"code":"USD","symbol":"&#36;","rate":"16,899.2795","description":"United States Dollar","rate_float":16899.2795},"GBP":{"code":"GBP","symbol":"&pound;","rate":"14,120.9028","description":"British Pound Sterling","rate_float":14120.9028},"EUR":{"code":"EUR","symbol":"&euro;","rate":"16,462.3656","description":"Euro","rate_float":16462.3656},"CNY":{"code":"CNY","symbol":"&yen;","rate":"40,202.5000","description":"Chinese Yuan","rate_float":40202.5}}}