{"time":{"updated":"Oct 15, 2024 07:18:43 UTC","updatedISO":"2024-10-15T07:18:43+00:00","updateduk":"Oct 15, 2024 at 08:18 BST"},"disclaimer":"This data was produced from the CoinDesk Bitcoin Price Index (USD). Non-USD currency data converted using hourly conversion rate from openexchangerates.org","chartName":"Bitcoin","bpi":{"USD":{"code":"USD","symbol":"&#36;","rate":"65,688.922","description":"United States Dollar","rate_float":65688.9221},"GBP":{"code":"GBP","symbol":"&pound;","rate":"50,339.72","description":"British Pound Sterling","rate_float":50339.7201},"EUR":{"code":"EUR","symbol":"&euro;","rate":"60,305.978","description":"Euro","rate_float":60305.9777},"CNY":{"code":"CNY","symbol":"&yen;","rate":"467,310.992","description":"Chinese Yuan","rate_float":467310.9918}}}