{"time":{"updated":"Dec 29, 2024 21:04:43 UTC","updatedISO":"2024-12-29T21:04:43+00:00","updateduk":"Dec 29, 2024 at 21:04 GMT"},"disclaimer":"This data was produced from the CoinDesk Bitcoin Price Index (USD). Non-USD currency data converted using hourly conversion rate from openexchangerates.org","chartName":"Bitcoin","bpi":{"USD":{"code":"USD","symbol":"&#36;","rate":"93,596.494","description":"United States Dollar","rate_float":93596.4939},"GBP":{"code":"GBP","symbol":"&pound;","rate":"74,641.332","description":"British Pound Sterling","rate_float":74641.3319},"EUR":{"code":"EUR","symbol":"&euro;","rate":"89,793.762","description":"Euro","rate_float":89793.7619},"CNY":{"code":"CNY","symbol":"&yen;","rate":"683,123.37","description":"Chinese Yuan","rate_float":683123.3703}}}