{"time":{"updated":"Jul 21, 2024 17:40:35 UTC","updatedISO":"2024-07-21T17:40:35+00:00","updateduk":"Jul 21, 2024 at 18:40 BST"},"disclaimer":"This data was produced from the CoinDesk Bitcoin Price Index (USD). Non-USD currency data converted using hourly conversion rate from openexchangerates.org","chartName":"Bitcoin","bpi":{"USD":{"code":"USD","symbol":"&#36;","rate":"67,426.716","description":"United States Dollar","rate_float":67426.7162},"GBP":{"code":"GBP","symbol":"&pound;","rate":"52,197.988","description":"British Pound Sterling","rate_float":52197.9878},"EUR":{"code":"EUR","symbol":"&euro;","rate":"61,930.427","description":"Euro","rate_float":61930.4274},"CNY":{"code":"CNY","symbol":"&yen;","rate":"490,192.227","description":"Chinese Yuan","rate_float":490192.2266}}}