{"time":{"updated":"Nov 1, 2024 14:12:25 UTC","updatedISO":"2024-11-01T14:12:25+00:00","updateduk":"Nov 1, 2024 at 14:12 GMT"},"disclaimer":"This data was produced from the CoinDesk Bitcoin Price Index (USD). Non-USD currency data converted using hourly conversion rate from openexchangerates.org","chartName":"Bitcoin","bpi":{"USD":{"code":"USD","symbol":"&#36;","rate":"71,406.56","description":"United States Dollar","rate_float":71406.5599},"GBP":{"code":"GBP","symbol":"&pound;","rate":"55,123.151","description":"British Pound Sterling","rate_float":55123.1508},"EUR":{"code":"EUR","symbol":"&euro;","rate":"65,590.781","description":"Euro","rate_float":65590.7813},"CNY":{"code":"CNY","symbol":"&yen;","rate":"507,772.048","description":"Chinese Yuan","rate_float":507772.0477}}}