{"time":{"updated":"Oct 21, 2024 18:32:59 UTC","updatedISO":"2024-10-21T18:32:59+00:00","updateduk":"Oct 21, 2024 at 19:32 BST"},"disclaimer":"This data was produced from the CoinDesk Bitcoin Price Index (USD). Non-USD currency data converted using hourly conversion rate from openexchangerates.org","chartName":"Bitcoin","bpi":{"USD":{"code":"USD","symbol":"&#36;","rate":"67,056.441","description":"United States Dollar","rate_float":67056.4412},"GBP":{"code":"GBP","symbol":"&pound;","rate":"51,630.912","description":"British Pound Sterling","rate_float":51630.9116},"EUR":{"code":"EUR","symbol":"&euro;","rate":"61,995.289","description":"Euro","rate_float":61995.2893},"CNY":{"code":"CNY","symbol":"&yen;","rate":"477,421.745","description":"Chinese Yuan","rate_float":477421.7446}}}