{"time":{"updated":"Jun 29, 2024 07:04:32 UTC","updatedISO":"2024-06-29T07:04:32+00:00","updateduk":"Jun 29, 2024 at 08:04 BST"},"disclaimer":"This data was produced from the CoinDesk Bitcoin Price Index (USD). Non-USD currency data converted using hourly conversion rate from openexchangerates.org","chartName":"Bitcoin","bpi":{"USD":{"code":"USD","symbol":"&#36;","rate":"60,820.182","description":"United States Dollar","rate_float":60820.182},"GBP":{"code":"GBP","symbol":"&pound;","rate":"48,082.976","description":"British Pound Sterling","rate_float":48082.9762},"EUR":{"code":"EUR","symbol":"&euro;","rate":"56,734.343","description":"Euro","rate_float":56734.343},"CNY":{"code":"CNY","symbol":"&yen;","rate":"441,998.509","description":"Chinese Yuan","rate_float":441998.5086}}}