{"time":{"updated":"Sep 9, 2024 07:40:06 UTC","updatedISO":"2024-09-09T07:40:06+00:00","updateduk":"Sep 9, 2024 at 08:40 BST"},"disclaimer":"This data was produced from the CoinDesk Bitcoin Price Index (USD). Non-USD currency data converted using hourly conversion rate from openexchangerates.org","chartName":"Bitcoin","bpi":{"USD":{"code":"USD","symbol":"&#36;","rate":"55,046.393","description":"United States Dollar","rate_float":55046.3926},"GBP":{"code":"GBP","symbol":"&pound;","rate":"42,012.178","description":"British Pound Sterling","rate_float":42012.1775},"EUR":{"code":"EUR","symbol":"&euro;","rate":"49,749.829","description":"Euro","rate_float":49749.8287},"CNY":{"code":"CNY","symbol":"&yen;","rate":"391,308.291","description":"Chinese Yuan","rate_float":391308.2912}}}