{"time":{"updated":"Dec 24, 2024 02:04:04 UTC","updatedISO":"2024-12-24T02:04:04+00:00","updateduk":"Dec 24, 2024 at 02:04 GMT"},"disclaimer":"This data was produced from the CoinDesk Bitcoin Price Index (USD). Non-USD currency data converted using hourly conversion rate from openexchangerates.org","chartName":"Bitcoin","bpi":{"USD":{"code":"USD","symbol":"&#36;","rate":"94,285.234","description":"United States Dollar","rate_float":94285.2338},"GBP":{"code":"GBP","symbol":"&pound;","rate":"75,210.483","description":"British Pound Sterling","rate_float":75210.4825},"EUR":{"code":"EUR","symbol":"&euro;","rate":"90,603.773","description":"Euro","rate_float":90603.7726},"CNY":{"code":"CNY","symbol":"&yen;","rate":"688,121.922","description":"Chinese Yuan","rate_float":688121.922}}}