{"time":{"updated":"Oct 6, 2024 22:15:05 UTC","updatedISO":"2024-10-06T22:15:05+00:00","updateduk":"Oct 6, 2024 at 23:15 BST"},"disclaimer":"This data was produced from the CoinDesk Bitcoin Price Index (USD). Non-USD currency data converted using hourly conversion rate from openexchangerates.org","chartName":"Bitcoin","bpi":{"USD":{"code":"USD","symbol":"&#36;","rate":"62,486.728","description":"United States Dollar","rate_float":62486.728},"GBP":{"code":"GBP","symbol":"&pound;","rate":"47,645.068","description":"British Pound Sterling","rate_float":47645.0678},"EUR":{"code":"EUR","symbol":"&euro;","rate":"56,974.524","description":"Euro","rate_float":56974.5238},"CNY":{"code":"CNY","symbol":"&yen;","rate":"438,949.269","description":"Chinese Yuan","rate_float":438949.2685}}}