{"time":{"updated":"May 18, 2024 08:33:11 UTC","updatedISO":"2024-05-18T08:33:11+00:00","updateduk":"May 18, 2024 at 09:33 BST"},"disclaimer":"This data was produced from the CoinDesk Bitcoin Price Index (USD). Non-USD currency data converted using hourly conversion rate from openexchangerates.org","chartName":"Bitcoin","bpi":{"USD":{"code":"USD","symbol":"&#36;","rate":"67,003.149","description":"United States Dollar","rate_float":67003.1489},"GBP":{"code":"GBP","symbol":"&pound;","rate":"52,737.643","description":"British Pound Sterling","rate_float":52737.6425},"EUR":{"code":"EUR","symbol":"&euro;","rate":"61,585.944","description":"Euro","rate_float":61585.9443},"CNY":{"code":"CNY","symbol":"&yen;","rate":"484,003.947","description":"Chinese Yuan","rate_float":484003.9466}}}