{"time":{"updated":"Sep 8, 2024 07:32:45 UTC","updatedISO":"2024-09-08T07:32:45+00:00","updateduk":"Sep 8, 2024 at 08:32 BST"},"disclaimer":"This data was produced from the CoinDesk Bitcoin Price Index (USD). Non-USD currency data converted using hourly conversion rate from openexchangerates.org","chartName":"Bitcoin","bpi":{"USD":{"code":"USD","symbol":"&#36;","rate":"54,482.762","description":"United States Dollar","rate_float":54482.7624},"GBP":{"code":"GBP","symbol":"&pound;","rate":"41,482.249","description":"British Pound Sterling","rate_float":41482.2491},"EUR":{"code":"EUR","symbol":"&euro;","rate":"49,127.107","description":"Euro","rate_float":49127.1068},"CNY":{"code":"CNY","symbol":"&yen;","rate":"386,222.854","description":"Chinese Yuan","rate_float":386222.8541}}}