{"time":{"updated":"Apr 23, 2022 18:28:00 UTC","updatedISO":"2022-04-23T18:28:00+00:00","updateduk":"Apr 23, 2022 at 19:28 BST"},"disclaimer":"This data was produced from the CoinDesk Bitcoin Price Index (USD). Non-USD currency data converted using hourly conversion rate from openexchangerates.org","chartName":"Bitcoin","bpi":{"USD":{"code":"USD","symbol":"&#36;","rate":"39,826.2151","description":"United States Dollar","rate_float":39826.2151},"GBP":{"code":"GBP","symbol":"&pound;","rate":"31,022.1523","description":"British Pound Sterling","rate_float":31022.1523},"EUR":{"code":"EUR","symbol":"&euro;","rate":"36,921.6096","description":"Euro","rate_float":36921.6096},"CNY":{"code":"CNY","symbol":"&yen;","rate":"40,202.5000","description":"Chinese Yuan","rate_float":40202.5}}}