{"time":{"updated":"Jun 12, 2024 04:35:58 UTC","updatedISO":"2024-06-12T04:35:58+00:00","updateduk":"Jun 12, 2024 at 05:35 BST"},"disclaimer":"This data was produced from the CoinDesk Bitcoin Price Index (USD). Non-USD currency data converted using hourly conversion rate from openexchangerates.org","chartName":"Bitcoin","bpi":{"USD":{"code":"USD","symbol":"&#36;","rate":"67,603.921","description":"United States Dollar","rate_float":67603.9214},"GBP":{"code":"GBP","symbol":"&pound;","rate":"53,051.163","description":"British Pound Sterling","rate_float":53051.1633},"EUR":{"code":"EUR","symbol":"&euro;","rate":"62,944.254","description":"Euro","rate_float":62944.2535},"CNY":{"code":"CNY","symbol":"&yen;","rate":"480,488.111","description":"Chinese Yuan","rate_float":480488.1109}}}