{"time":{"updated":"Mar 13, 2024 04:12:11 UTC","updatedISO":"2024-03-13T04:12:11+00:00","updateduk":"Mar 13, 2024 at 04:12 GMT"},"disclaimer":"This data was produced from the CoinDesk Bitcoin Price Index (USD). Non-USD currency data converted using hourly conversion rate from openexchangerates.org","chartName":"Bitcoin","bpi":{"USD":{"code":"USD","symbol":"&#36;","rate":"72,066.509","description":"United States Dollar","rate_float":72066.5089},"GBP":{"code":"GBP","symbol":"&pound;","rate":"56,325.598","description":"British Pound Sterling","rate_float":56325.5979},"EUR":{"code":"EUR","symbol":"&euro;","rate":"65,943.594","description":"Euro","rate_float":65943.5942},"CNY":{"code":"CNY","symbol":"&yen;","rate":"518,006.86","description":"Chinese Yuan","rate_float":518006.8595}}}