{"time":{"updated":"Apr 15, 2024 04:25:58 UTC","updatedISO":"2024-04-15T04:25:58+00:00","updateduk":"Apr 15, 2024 at 05:25 BST"},"disclaimer":"This data was produced from the CoinDesk Bitcoin Price Index (USD). Non-USD currency data converted using hourly conversion rate from openexchangerates.org","chartName":"Bitcoin","bpi":{"USD":{"code":"USD","symbol":"&#36;","rate":"65,137.112","description":"United States Dollar","rate_float":65137.1123},"GBP":{"code":"GBP","symbol":"&pound;","rate":"52,276.376","description":"British Pound Sterling","rate_float":52276.3757},"EUR":{"code":"EUR","symbol":"&euro;","rate":"61,157.56","description":"Euro","rate_float":61157.5604},"CNY":{"code":"CNY","symbol":"&yen;","rate":"471,475.446","description":"Chinese Yuan","rate_float":471475.4463}}}