{"time":{"updated":"Jun 2, 2024 22:57:50 UTC","updatedISO":"2024-06-02T22:57:50+00:00","updateduk":"Jun 2, 2024 at 23:57 BST"},"disclaimer":"This data was produced from the CoinDesk Bitcoin Price Index (USD). Non-USD currency data converted using hourly conversion rate from openexchangerates.org","chartName":"Bitcoin","bpi":{"USD":{"code":"USD","symbol":"&#36;","rate":"67,907.861","description":"United States Dollar","rate_float":67907.861},"GBP":{"code":"GBP","symbol":"&pound;","rate":"53,303.529","description":"British Pound Sterling","rate_float":53303.5285},"EUR":{"code":"EUR","symbol":"&euro;","rate":"62,598.145","description":"Euro","rate_float":62598.1454},"CNY":{"code":"CNY","symbol":"&yen;","rate":"486,181.51","description":"Chinese Yuan","rate_float":486181.5095}}}