{"time":{"updated":"Jan 29, 2024 19:46:44 UTC","updatedISO":"2024-01-29T19:46:44+00:00","updateduk":"Jan 29, 2024 at 19:46 GMT"},"disclaimer":"This data was produced from the CoinDesk Bitcoin Price Index (USD). Non-USD currency data converted using hourly conversion rate from openexchangerates.org","chartName":"Bitcoin","bpi":{"USD":{"code":"USD","symbol":"&#36;","rate":"43,079.398","description":"United States Dollar","rate_float":43079.3977},"GBP":{"code":"GBP","symbol":"&pound;","rate":"33,965.822","description":"British Pound Sterling","rate_float":33965.8219},"EUR":{"code":"EUR","symbol":"&euro;","rate":"39,844.695","description":"Euro","rate_float":39844.695},"CNY":{"code":"CNY","symbol":"&yen;","rate":"307,621.363","description":"Chinese Yuan","rate_float":307621.3631}}}