{"time":{"updated":"May 2, 2024 04:35:24 UTC","updatedISO":"2024-05-02T04:35:24+00:00","updateduk":"May 2, 2024 at 05:35 BST"},"disclaimer":"This data was produced from the CoinDesk Bitcoin Price Index (USD). Non-USD currency data converted using hourly conversion rate from openexchangerates.org","chartName":"Bitcoin","bpi":{"USD":{"code":"USD","symbol":"&#36;","rate":"57,593.319","description":"United States Dollar","rate_float":57593.3194},"GBP":{"code":"GBP","symbol":"&pound;","rate":"45,962.694","description":"British Pound Sterling","rate_float":45962.6941},"EUR":{"code":"EUR","symbol":"&euro;","rate":"53,749.541","description":"Euro","rate_float":53749.5412},"CNY":{"code":"CNY","symbol":"&yen;","rate":"417,027.466","description":"Chinese Yuan","rate_float":417027.4662}}}