{"time":{"updated":"Jun 20, 2024 20:51:57 UTC","updatedISO":"2024-06-20T20:51:57+00:00","updateduk":"Jun 20, 2024 at 21:51 BST"},"disclaimer":"This data was produced from the CoinDesk Bitcoin Price Index (USD). Non-USD currency data converted using hourly conversion rate from openexchangerates.org","chartName":"Bitcoin","bpi":{"USD":{"code":"USD","symbol":"&#36;","rate":"65,040.4","description":"United States Dollar","rate_float":65040.4},"GBP":{"code":"GBP","symbol":"&pound;","rate":"51,360.843","description":"British Pound Sterling","rate_float":51360.8429},"EUR":{"code":"EUR","symbol":"&euro;","rate":"60,755.799","description":"Euro","rate_float":60755.7986},"CNY":{"code":"CNY","symbol":"&yen;","rate":"472,206.312","description":"Chinese Yuan","rate_float":472206.3122}}}