{"time":{"updated":"Oct 14, 2024 10:17:24 UTC","updatedISO":"2024-10-14T10:17:24+00:00","updateduk":"Oct 14, 2024 at 11:17 BST"},"disclaimer":"This data was produced from the CoinDesk Bitcoin Price Index (USD). Non-USD currency data converted using hourly conversion rate from openexchangerates.org","chartName":"Bitcoin","bpi":{"USD":{"code":"USD","symbol":"&#36;","rate":"64,803.432","description":"United States Dollar","rate_float":64803.4317},"GBP":{"code":"GBP","symbol":"&pound;","rate":"49,643.058","description":"British Pound Sterling","rate_float":49643.0577},"EUR":{"code":"EUR","symbol":"&euro;","rate":"59,295.075","description":"Euro","rate_float":59295.0752},"CNY":{"code":"CNY","symbol":"&yen;","rate":"458,834.218","description":"Chinese Yuan","rate_float":458834.2181}}}