{"time":{"updated":"Jun 1, 2024 17:09:45 UTC","updatedISO":"2024-06-01T17:09:45+00:00","updateduk":"Jun 1, 2024 at 18:09 BST"},"disclaimer":"This data was produced from the CoinDesk Bitcoin Price Index (USD). Non-USD currency data converted using hourly conversion rate from openexchangerates.org","chartName":"Bitcoin","bpi":{"USD":{"code":"USD","symbol":"&#36;","rate":"67,699.324","description":"United States Dollar","rate_float":67699.3239},"GBP":{"code":"GBP","symbol":"&pound;","rate":"53,151.687","description":"British Pound Sterling","rate_float":53151.687},"EUR":{"code":"EUR","symbol":"&euro;","rate":"62,358.321","description":"Euro","rate_float":62358.3211},"CNY":{"code":"CNY","symbol":"&yen;","rate":"481,064.626","description":"Chinese Yuan","rate_float":481064.6256}}}