{"time":{"updated":"Sep 28, 2024 20:52:29 UTC","updatedISO":"2024-09-28T20:52:29+00:00","updateduk":"Sep 28, 2024 at 21:52 BST"},"disclaimer":"This data was produced from the CoinDesk Bitcoin Price Index (USD). Non-USD currency data converted using hourly conversion rate from openexchangerates.org","chartName":"Bitcoin","bpi":{"USD":{"code":"USD","symbol":"&#36;","rate":"65,744.491","description":"United States Dollar","rate_float":65744.4914},"GBP":{"code":"GBP","symbol":"&pound;","rate":"49,169.45","description":"British Pound Sterling","rate_float":49169.4504},"EUR":{"code":"EUR","symbol":"&euro;","rate":"58,850.195","description":"Euro","rate_float":58850.1953},"CNY":{"code":"CNY","symbol":"&yen;","rate":"460,980.65","description":"Chinese Yuan","rate_float":460980.6503}}}