{"time":{"updated":"Jan 5, 2025 16:32:22 UTC","updatedISO":"2025-01-05T16:32:22+00:00","updateduk":"Jan 5, 2025 at 16:32 GMT"},"disclaimer":"This data was produced from the CoinDesk Bitcoin Price Index (USD). Non-USD currency data converted using hourly conversion rate from openexchangerates.org","chartName":"Bitcoin","bpi":{"USD":{"code":"USD","symbol":"&#36;","rate":"99,048.739","description":"United States Dollar","rate_float":99048.7389},"GBP":{"code":"GBP","symbol":"&pound;","rate":"78,989.388","description":"British Pound Sterling","rate_float":78989.3883},"EUR":{"code":"EUR","symbol":"&euro;","rate":"95,024.488","description":"Euro","rate_float":95024.4876},"CNY":{"code":"CNY","symbol":"&yen;","rate":"722,917.125","description":"Chinese Yuan","rate_float":722917.1254}}}