{"time":{"updated":"Dec 14, 2022 17:12:00 UTC","updatedISO":"2022-12-14T17:12:00+00:00","updateduk":"Dec 14, 2022 at 17:12 GMT"},"disclaimer":"This data was produced from the CoinDesk Bitcoin Price Index (USD). Non-USD currency data converted using hourly conversion rate from openexchangerates.org","chartName":"Bitcoin","bpi":{"USD":{"code":"USD","symbol":"&#36;","rate":"18,118.5170","description":"United States Dollar","rate_float":18118.517},"GBP":{"code":"GBP","symbol":"&pound;","rate":"15,139.6879","description":"British Pound Sterling","rate_float":15139.6879},"EUR":{"code":"EUR","symbol":"&euro;","rate":"17,650.0809","description":"Euro","rate_float":17650.0809},"CNY":{"code":"CNY","symbol":"&yen;","rate":"40,202.5000","description":"Chinese Yuan","rate_float":40202.5}}}