{"time":{"updated":"Jul 16, 2024 03:47:49 UTC","updatedISO":"2024-07-16T03:47:49+00:00","updateduk":"Jul 16, 2024 at 04:47 BST"},"disclaimer":"This data was produced from the CoinDesk Bitcoin Price Index (USD). Non-USD currency data converted using hourly conversion rate from openexchangerates.org","chartName":"Bitcoin","bpi":{"USD":{"code":"USD","symbol":"&#36;","rate":"64,698.094","description":"United States Dollar","rate_float":64698.0935},"GBP":{"code":"GBP","symbol":"&pound;","rate":"49,908.692","description":"British Pound Sterling","rate_float":49908.6916},"EUR":{"code":"EUR","symbol":"&euro;","rate":"59,404.107","description":"Euro","rate_float":59404.1073},"CNY":{"code":"CNY","symbol":"&yen;","rate":"469,701.689","description":"Chinese Yuan","rate_float":469701.6889}}}