{"time":{"updated":"May 31, 2023 14:45:00 UTC","updatedISO":"2023-05-31T14:45:00+00:00","updateduk":"May 31, 2023 at 15:45 BST"},"disclaimer":"This data was produced from the CoinDesk Bitcoin Price Index (USD). Non-USD currency data converted using hourly conversion rate from openexchangerates.org","chartName":"Bitcoin","bpi":{"USD":{"code":"USD","symbol":"&#36;","rate":"26,985.7822","description":"United States Dollar","rate_float":26985.7822},"GBP":{"code":"GBP","symbol":"&pound;","rate":"22,549.1037","description":"British Pound Sterling","rate_float":22549.1037},"EUR":{"code":"EUR","symbol":"&euro;","rate":"26,288.0918","description":"Euro","rate_float":26288.0918},"CNY":{"code":"CNY","symbol":"&yen;","rate":"40,202.5000","description":"Chinese Yuan","rate_float":40202.5}}}