{"time":{"updated":"May 4, 2022 05:44:00 UTC","updatedISO":"2022-05-04T05:44:00+00:00","updateduk":"May 4, 2022 at 06:44 BST"},"disclaimer":"This data was produced from the CoinDesk Bitcoin Price Index (USD). Non-USD currency data converted using hourly conversion rate from openexchangerates.org","chartName":"Bitcoin","bpi":{"USD":{"code":"USD","symbol":"&#36;","rate":"38,041.5817","description":"United States Dollar","rate_float":38041.5817},"GBP":{"code":"GBP","symbol":"&pound;","rate":"30,476.9751","description":"British Pound Sterling","rate_float":30476.9751},"EUR":{"code":"EUR","symbol":"&euro;","rate":"36,172.3705","description":"Euro","rate_float":36172.3705},"CNY":{"code":"CNY","symbol":"&yen;","rate":"40,202.5000","description":"Chinese Yuan","rate_float":40202.5}}}