{"time":{"updated":"Oct 9, 2021 19:23:00 UTC","updatedISO":"2021-10-09T19:23:00+00:00","updateduk":"Oct 9, 2021 at 20:23 BST"},"disclaimer":"This data was produced from the CoinDesk Bitcoin Price Index (USD). Non-USD currency data converted using hourly conversion rate from openexchangerates.org","chartName":"Bitcoin","bpi":{"USD":{"code":"USD","symbol":"&#36;","rate":"54,785.7653","description":"United States Dollar","rate_float":54785.7653},"GBP":{"code":"GBP","symbol":"&pound;","rate":"40,243.7057","description":"British Pound Sterling","rate_float":40243.7057},"EUR":{"code":"EUR","symbol":"&euro;","rate":"47,350.5699","description":"Euro","rate_float":47350.5699},"CNY":{"code":"CNY","symbol":"&yen;","rate":"40,202.5000","description":"Chinese Yuan","rate_float":40202.5}}}