{"time":{"updated":"Mar 29, 2024 02:46:02 UTC","updatedISO":"2024-03-29T02:46:02+00:00","updateduk":"Mar 29, 2024 at 02:46 GMT"},"disclaimer":"This data was produced from the CoinDesk Bitcoin Price Index (USD). Non-USD currency data converted using hourly conversion rate from openexchangerates.org","chartName":"Bitcoin","bpi":{"USD":{"code":"USD","symbol":"&#36;","rate":"70,621.037","description":"United States Dollar","rate_float":70621.0365},"GBP":{"code":"GBP","symbol":"&pound;","rate":"55,937.44","description":"British Pound Sterling","rate_float":55937.44},"EUR":{"code":"EUR","symbol":"&euro;","rate":"65,535.757","description":"Euro","rate_float":65535.7569},"CNY":{"code":"CNY","symbol":"&yen;","rate":"510,427.666","description":"Chinese Yuan","rate_float":510427.6658}}}