{"time":{"updated":"Mar 16, 2023 06:42:00 UTC","updatedISO":"2023-03-16T06:42:00+00:00","updateduk":"Mar 16, 2023 at 06:42 GMT"},"disclaimer":"This data was produced from the CoinDesk Bitcoin Price Index (USD). Non-USD currency data converted using hourly conversion rate from openexchangerates.org","chartName":"Bitcoin","bpi":{"USD":{"code":"USD","symbol":"&#36;","rate":"24,479.6444","description":"United States Dollar","rate_float":24479.6444},"GBP":{"code":"GBP","symbol":"&pound;","rate":"20,454.9950","description":"British Pound Sterling","rate_float":20454.995},"EUR":{"code":"EUR","symbol":"&euro;","rate":"23,846.7477","description":"Euro","rate_float":23846.7477},"CNY":{"code":"CNY","symbol":"&yen;","rate":"40,202.5000","description":"Chinese Yuan","rate_float":40202.5}}}