{"time":{"updated":"Sep 1, 2024 09:04:39 UTC","updatedISO":"2024-09-01T09:04:39+00:00","updateduk":"Sep 1, 2024 at 10:04 BST"},"disclaimer":"This data was produced from the CoinDesk Bitcoin Price Index (USD). Non-USD currency data converted using hourly conversion rate from openexchangerates.org","chartName":"Bitcoin","bpi":{"USD":{"code":"USD","symbol":"&#36;","rate":"58,218.536","description":"United States Dollar","rate_float":58218.536},"GBP":{"code":"GBP","symbol":"&pound;","rate":"44,338.422","description":"British Pound Sterling","rate_float":44338.4219},"EUR":{"code":"EUR","symbol":"&euro;","rate":"52,636.426","description":"Euro","rate_float":52636.4263},"CNY":{"code":"CNY","symbol":"&yen;","rate":"412,949.898","description":"Chinese Yuan","rate_float":412949.8976}}}