{"time":{"updated":"Feb 17, 2024 22:45:24 UTC","updatedISO":"2024-02-17T22:45:24+00:00","updateduk":"Feb 17, 2024 at 22:45 GMT"},"disclaimer":"This data was produced from the CoinDesk Bitcoin Price Index (USD). Non-USD currency data converted using hourly conversion rate from openexchangerates.org","chartName":"Bitcoin","bpi":{"USD":{"code":"USD","symbol":"&#36;","rate":"51,659.932","description":"United States Dollar","rate_float":51659.9319},"GBP":{"code":"GBP","symbol":"&pound;","rate":"40,993.448","description":"British Pound Sterling","rate_float":40993.4475},"EUR":{"code":"EUR","symbol":"&euro;","rate":"47,935.767","description":"Euro","rate_float":47935.7674},"CNY":{"code":"CNY","symbol":"&yen;","rate":"367,782.553","description":"Chinese Yuan","rate_float":367782.5532}}}