{"time":{"updated":"Apr 11, 2024 18:07:25 UTC","updatedISO":"2024-04-11T18:07:25+00:00","updateduk":"Apr 11, 2024 at 19:07 BST"},"disclaimer":"This data was produced from the CoinDesk Bitcoin Price Index (USD). Non-USD currency data converted using hourly conversion rate from openexchangerates.org","chartName":"Bitcoin","bpi":{"USD":{"code":"USD","symbol":"&#36;","rate":"70,257.92","description":"United States Dollar","rate_float":70257.9201},"GBP":{"code":"GBP","symbol":"&pound;","rate":"56,040.036","description":"British Pound Sterling","rate_float":56040.0356},"EUR":{"code":"EUR","symbol":"&euro;","rate":"65,553.309","description":"Euro","rate_float":65553.3092},"CNY":{"code":"CNY","symbol":"&yen;","rate":"508,484.671","description":"Chinese Yuan","rate_float":508484.6707}}}