{"time":{"updated":"Jun 17, 2024 15:52:54 UTC","updatedISO":"2024-06-17T15:52:54+00:00","updateduk":"Jun 17, 2024 at 16:52 BST"},"disclaimer":"This data was produced from the CoinDesk Bitcoin Price Index (USD). Non-USD currency data converted using hourly conversion rate from openexchangerates.org","chartName":"Bitcoin","bpi":{"USD":{"code":"USD","symbol":"&#36;","rate":"65,428.703","description":"United States Dollar","rate_float":65428.7034},"GBP":{"code":"GBP","symbol":"&pound;","rate":"51,602.179","description":"British Pound Sterling","rate_float":51602.1789},"EUR":{"code":"EUR","symbol":"&euro;","rate":"61,057.804","description":"Euro","rate_float":61057.8043},"CNY":{"code":"CNY","symbol":"&yen;","rate":"474,763.758","description":"Chinese Yuan","rate_float":474763.7575}}}