{"time":{"updated":"Feb 6, 2024 16:03:50 UTC","updatedISO":"2024-02-06T16:03:50+00:00","updateduk":"Feb 6, 2024 at 16:03 GMT"},"disclaimer":"This data was produced from the CoinDesk Bitcoin Price Index (USD). Non-USD currency data converted using hourly conversion rate from openexchangerates.org","chartName":"Bitcoin","bpi":{"USD":{"code":"USD","symbol":"&#36;","rate":"43,232.302","description":"United States Dollar","rate_float":43232.302},"GBP":{"code":"GBP","symbol":"&pound;","rate":"34,382.866","description":"British Pound Sterling","rate_float":34382.8659},"EUR":{"code":"EUR","symbol":"&euro;","rate":"40,249.403","description":"Euro","rate_float":40249.4028},"CNY":{"code":"CNY","symbol":"&yen;","rate":"307,217.384","description":"Chinese Yuan","rate_float":307217.3844}}}