{"time":{"updated":"Nov 29, 2024 14:43:33 UTC","updatedISO":"2024-11-29T14:43:33+00:00","updateduk":"Nov 29, 2024 at 14:43 GMT"},"disclaimer":"This data was produced from the CoinDesk Bitcoin Price Index (USD). Non-USD currency data converted using hourly conversion rate from openexchangerates.org","chartName":"Bitcoin","bpi":{"USD":{"code":"USD","symbol":"&#36;","rate":"97,585.786","description":"United States Dollar","rate_float":97585.7861},"GBP":{"code":"GBP","symbol":"&pound;","rate":"76,926.192","description":"British Pound Sterling","rate_float":76926.1921},"EUR":{"code":"EUR","symbol":"&euro;","rate":"92,384.854","description":"Euro","rate_float":92384.854},"CNY":{"code":"CNY","symbol":"&yen;","rate":"706,735.78","description":"Chinese Yuan","rate_float":706735.7798}}}