{"time":{"updated":"Sep 14, 2024 11:41:05 UTC","updatedISO":"2024-09-14T11:41:05+00:00","updateduk":"Sep 14, 2024 at 12:41 BST"},"disclaimer":"This data was produced from the CoinDesk Bitcoin Price Index (USD). Non-USD currency data converted using hourly conversion rate from openexchangerates.org","chartName":"Bitcoin","bpi":{"USD":{"code":"USD","symbol":"&#36;","rate":"59,747.43","description":"United States Dollar","rate_float":59747.4298},"GBP":{"code":"GBP","symbol":"&pound;","rate":"45,528.796","description":"British Pound Sterling","rate_float":45528.7962},"EUR":{"code":"EUR","symbol":"&euro;","rate":"53,892.062","description":"Euro","rate_float":53892.0622},"CNY":{"code":"CNY","symbol":"&yen;","rate":"423,818.393","description":"Chinese Yuan","rate_float":423818.3932}}}